jieba_path/__init__.py
jieba_path/jieba_path.py
jieba_path-0.0.1.7.dist-info/LICENSE
jieba_path-0.0.1.7.dist-info/METADATA
jieba_path-0.0.1.7.dist-info/WHEEL
jieba_path-0.0.1.7.dist-info/top_level.txt
jieba_path-0.0.1.7.dist-info/RECORD
