Metadata-Version: 2.1
Name: jieba-path
Version: 0.0.1.7
Summary: 结巴分词预处理目录下的文档
Home-page: https://www.terrychan.org/p/977
Author: author
Author-email: napoler2008@gmail.com
License: UNKNOWN
Platform: UNKNOWN
Requires-Dist: jieba
